mushpedia_scraper/__init__.py
mushpedia_scraper/cli.py
mushpedia_scraper/links.py
mushpedia_scraper/adapters/__init__.py
mushpedia_scraper/adapters/file_system_page_reader.py
mushpedia_scraper/adapters/http_page_reader.py
mushpedia_scraper/ports/__init__.py
mushpedia_scraper/ports/page_reader.py
mushpedia_scraper/usecases/__init__.py
mushpedia_scraper/usecases/scrap_mushpedia.py
mushpedia_scraper-0.4.0.dist-info/METADATA
mushpedia_scraper-0.4.0.dist-info/WHEEL
mushpedia_scraper-0.4.0.dist-info/entry_points.txt
mushpedia_scraper-0.4.0.dist-info/licenses/LICENSE
mushpedia_scraper-0.4.0.dist-info/RECORD
