Metadata-Version: 2.3
Name: mushpedia-scraper
Version: 0.4.0
Summary: Scraper for mushpedia.com
Author-email: Charles-Meldhine Madi Mnemoi <charlesmeldhine.madimnemoi@gmail.com>
License: MIT
Requires-Python: <3.14,>=3.9
Requires-Dist: beautifulsoup4>=4.12.3
Requires-Dist: httpx>=0.27.2
Requires-Dist: markdownify>=0.13.1
Requires-Dist: requests>=2.32.3
Requires-Dist: typer>=0.13.0
